[
    {
        "id": 0,
        "group": "ang2",
        "groupName": "Angular2",
        "snippets": [
            {
                "id": 0,
                "titleText": "Some Nice Snippet xxx dd ",
                "elements": [
                    {
                        "id": 0,
                        "type": "div",
                        "style": null,
                        "text": "This is <u>paragraph </u><b>entery </b>d d <i>dfsfd ss</i><h3><b>one<br></b><b>two&nbsp;</b></h3><div>three ads <i>dsa x</i></div>"
                    },
                    {
                        "id": 1,
                        "type": "pre",
                        "style": null,
                        "text": "This is pre block element xxx x"
                    },
                    {
                        "id": 2,
                        "type": "div",
                        "style": null,
                        "text": "<p>This fresh element</p>"
                    },
                    {
                        "id": 3,
                        "type": "pre",
                        "style": null,
                        "text": "<p><span class=\"tag\">&lt;div</span><span class=\"pln\"> </span><span class=\"atn\"><b><u>class</u></b></span><span class=\"pun\">=</span><span class=\"atv\">\"btn-group dropup\"</span><span class=\"tag\">&gt;</span></p><h3><span class=\"tag\">Some comment here</span></h3><p><span class=\"tag\">&lt;button</span><span class=\"pln\"> </span><span class=\"atn\">class</span><span class=\"pun\">=</span><span class=\"atv\">\"btn btn-secondary btn-sm dropdown-toggle\"</span><span class=\"pln\"> </span><span class=\"atn\">type</span><span class=\"pun\">=</span><span class=\"atv\">\"button\"</span><span class=\"pln\"> </span><span class=\"atn\">data-toggle</span><span class=\"pun\">=</span><span class=\"atv\">\"dropdown\"</span><span class=\"pln\"> </span><span class=\"atn\">aria-haspopup</span><span class=\"pun\">=</span><span class=\"atv\">\"true\"</span><span class=\"pln\"> </span><span class=\"atn\">aria-expanded</span><span class=\"pun\">=</span><span class=\"atv\">\"false\"</span><span class=\"tag\">&gt;</span></p><p><span class=\"pln\">Add Element</span></p><p><span class=\"tag\">&lt;/button&gt;</span></p><p><span class=\"tag\">&lt;div</span><span class=\"pln\"> </span><span class=\"atn\">class</span><span class=\"pun\">=</span><span class=\"atv\">\"dropdown-menu\"</span><span class=\"tag\">&gt;</span></p><p><span class=\"tag\">&lt;button</span><span class=\"pln\"> (</span><span class=\"atn\">click</span><span class=\"pln\">)</span><span class=\"pun\">=</span><span class=\"atv\">'addElementPre(snippet.elements)'</span><span class=\"pln\"> </span><span class=\"atn\">type</span><span class=\"pun\">=</span><span class=\"atv\">\"button\"</span><span class=\"pln\"> </span><span class=\"atn\">class</span><span class=\"pun\">=</span><span class=\"atv\">\"dropdown-item\"</span><span class=\"tag\">&gt;&lt;i</span><span class=\"pln\"> </span><span class=\"atn\">class</span><span class=\"pun\">=</span><span class=\"atv\">\"fa fa-plus\"</span><span class=\"pln\"> </span><span class=\"atn\">aria-hidden</span><span class=\"pun\">=</span><span class=\"atv\">\"true\"</span><span class=\"tag\">&gt;&lt;/i&gt;</span><span class=\"pln\"> Code Elem</span><span class=\"tag\">&lt;/button&gt;</span></p><p><span class=\"tag\">&lt;button</span><span class=\"pln\"> (</span><span class=\"atn\">click</span><span class=\"pln\">)</span><span class=\"pun\">=</span><span class=\"atv\">'addElementDiv(snippet.elements)'</span><span class=\"pln\"> </span><span class=\"atn\">type</span><span class=\"pun\">=</span><span class=\"atv\">\"button\"</span><span class=\"pln\"> </span><span class=\"atn\">class</span><span class=\"pun\">=</span><span class=\"atv\">\"dropdown-item\"</span><span class=\"tag\">&gt;&lt;i</span><span class=\"pln\"> </span><span class=\"atn\">class</span><span class=\"pun\">=</span><span class=\"atv\">\"fa fa-plus\"</span><span class=\"pln\"> </span><span class=\"atn\">aria-hidden</span><span class=\"pun\">=</span><span class=\"atv\">\"true\"</span><span class=\"tag\">&gt;&lt;/i&gt;</span><span class=\"pln\"> Simple Elem</span><span class=\"tag\">&lt;/button&gt;</span></p><p><span class=\"tag\">&lt;/div&gt;</span></p><p><span class=\"tag\">&lt;/div&gt;</span></p>"
                    }
                ],
                "comments": null
            },
            {
                "id": 1,
                "titleText": "Snippet 2",
                "elements": [
                    {
                        "id": 0,
                        "type": "div",
                        "style": null,
                        "text": "This is the title element"
                    },
                    {
                        "id": 1,
                        "type": "pre",
                        "style": null,
                        "text": "import {Component, ViewChild, ElementRef, AfterViewInit,OnInit, Inject} from '@angular/core';\nimport { AuthService } from '../user/auth.service';\nimport { ActivatedRoute } from '@angular/router';\nimport { JQUERY_TOKEN } from '../common/index'; \nimportimport\nimportimportimportimport@Component({\n    templateUrl:'./app/home/home.component.html',\n\t\tstyles:[`h1 {color:red;}`]\n})\n\n\nexport class HomeComponent implements OnInit {\n\t\tngOnInit(): void {\n\t\t\tthis.user = this.route.snapshot.data['user'];\n\t\t}\n\tuser:any;\n\tconstructor(\n\tprivate route:ActivatedRoute,\t\n\tprivate auth:AuthService,\n\t@Inject(JQUERY_TOKEN) private $){\n\t}\n  ngAfterViewInit() {\n    \n  }\n\tngOnChanges(){\n\t\tthis.user = this.auth.getCurrentUser();\n\t}\n\n\n}"
                    },
                    {
                        "id": 2,
                        "type": "div",
                        "style": null,
                        "text": "This is paragraph entery"
                    }
                ],
                "comments": null
            },
            {
                "id": 2,
                "titleText": "Snippet 1",
                "elements": [
                    {
                        "id": 0,
                        "type": "pre",
                        "style": null,
                        "text": "passport.serializeUser(function(user, done) {\n  done(null, user); \n});\n\npassport.deserializeUser(function(user, done) {\n  done(null, user);\n});\n\n\npassport.use('loginUsers', new LocalStrategy(\n\n  function(username, password, done) {\n     users.findOne({email: username}, function(err, user) {\n\n      if (err) { return done(err); }\n\n      if (!user) {\n\n        console.log('[+] DB: user/password failure'.red);\n        return done(null, false, {error: ''});\n\n      }else if(!bcrypt.compareSync(password, user.hashed_password)){\n\n        console.log((\"[+] Password error\").red);\n        return done(null, false, {error: ''});\n\n      }else if(user.verified === false){\n\n            console.log(\"[+] DB: user not verified\");\n            return done(null, false, {error: ''});\n\n      }else{\n\n      console.log(\"[+] DB: user/password success\".green);\n      return done(null, user);\n      }  //else\n    }); //findOne\n  }\n));"
                    },
                    {
                        "id": 1,
                        "type": "div",
                        "style": null,
                        "text": "xxxxxxx<div>dsdsds</div><div>dsdsds</div><div>dsdsds</div><div>dsds</div>"
                    },
                    {
                        "id": 2,
                        "type": "div",
                        "style": null,
                        "text": "This is the title element"
                    }
                ],
                "comments": [
                    {
                        "when": "today",
                        "who": "user2",
                        "what": "user comment here"
                    },
                    {
                        "when": "today",
                        "who": "user1",
                        "what": "user comment here"
                    }
                ]
            },
            {
                "titleText": "New Snippet",
                "elements": [
                    {
                        "id": 0,
                        "type": "div",
                        "style": null,
                        "text": "This is the title element"
                    },
                    {
                        "id": 1,
                        "type": "div",
                        "style": null,
                        "text": "This is paragraph entery"
                    },
                    {
                        "id": 2,
                        "type": "pre",
                        "style": null,
                        "text": "This is pre block element"
                    }
                ],
                "comments": null
            },
            {
                "titleText": "New Snippet",
                "elements": [
                    {
                        "id": 0,
                        "type": "div",
                        "style": null,
                        "text": "This is the title element"
                    },
                    {
                        "id": 1,
                        "type": "div",
                        "style": null,
                        "text": "This is paragraph entery"
                    },
                    {
                        "id": 2,
                        "type": "pre",
                        "style": null,
                        "text": "This is pre block element"
                    }
                ],
                "comments": null
            },
            {
                "titleText": "My New Code Snippet",
                "elements": [
                    {
                        "id": 0,
                        "type": "div",
                        "style": null,
                        "text": "This is the title element"
                    },
                    {
                        "id": 1,
                        "type": "div",
                        "style": null,
                        "text": "This is paragraph entery"
                    },
                    {
                        "id": 2,
                        "type": "pre",
                        "style": null,
                        "text": "This is pre block element"
                    }
                ],
                "comments": null
            },
            {
                "titleText": "New Snippet",
                "elements": [
                    {
                        "id": 0,
                        "type": "div",
                        "style": null,
                        "text": "This is the title element"
                    },
                    {
                        "id": 1,
                        "type": "div",
                        "style": null,
                        "text": "This is paragraph entery"
                    },
                    {
                        "id": 2,
                        "type": "pre",
                        "style": null,
                        "text": "This is pre block element xxx"
                    }
                ],
                "comments": null
            },
            {
                "titleText": "New Snippet",
                "elements": [
                    {
                        "id": 0,
                        "type": "div",
                        "style": null,
                        "text": "This is the <b><i>title </i></b><u>element&nbsp;</u>"
                    },
                    {
                        "id": 1,
                        "type": "div",
                        "style": null,
                        "text": "This is paragraph entery"
                    },
                    {
                        "id": 2,
                        "type": "pre",
                        "style": null,
                        "text": "This is pre block element"
                    }
                ],
                "comments": null
            }
        ]
    },
    {
        "id": 1,
        "group": "plsql",
        "groupName": "PL/SQL",
        "snippets": [
            {
                "id": 0,
                "titleText": "Snippet 1",
                "elements": [
                    {
                        "id": 0,
                        "type": "div",
                        "style": null,
                        "text": "This is the title element"
                    },
                    {
                        "id": 1,
                        "type": "pre",
                        "style": null,
                        "text": "This is pre block element"
                    },
                    {
                        "id": 2,
                        "type": "div",
                        "style": null,
                        "text": "This is paragraph entery"
                    }
                ],
                "comments": null
            },
            {
                "id": 1,
                "titleText": "Snippet 2",
                "elements": [
                    {
                        "id": 0,
                        "type": "div",
                        "style": null,
                        "text": "This is the title element"
                    },
                    {
                        "id": 1,
                        "type": "pre",
                        "style": null,
                        "text": "This is pre block element"
                    },
                    {
                        "id": 2,
                        "type": "div",
                        "style": null,
                        "text": "This is paragraph entery"
                    }
                ],
                "comments": null
            },
            {
                "id": 2,
                "titleText": "Snippet 3",
                "elements": [
                    {
                        "id": 0,
                        "type": "div",
                        "style": null,
                        "text": "This is the title element"
                    },
                    {
                        "id": 1,
                        "type": "pre",
                        "style": null,
                        "text": "This is pre block element"
                    },
                    {
                        "id": 2,
                        "type": "div",
                        "style": null,
                        "text": "This is paragraph entery"
                    }
                ],
                "comments": null
            }
        ]
    },
    {
        "id": 2,
        "group": "java",
        "groupName": "JAVA",
        "snippets": [
            {
                "id": 0,
                "titleText": "Snippet 1",
                "elements": [
                    {
                        "id": 0,
                        "type": "div",
                        "style": null,
                        "text": "This is the title element"
                    },
                    {
                        "id": 1,
                        "type": "pre",
                        "style": null,
                        "text": "This is pre block element"
                    },
                    {
                        "id": 2,
                        "type": "div",
                        "style": null,
                        "text": "This is paragraph entery"
                    }
                ],
                "comments": null
            },
            {
                "id": 1,
                "titleText": "Snippet 2",
                "elements": [
                    {
                        "id": 0,
                        "type": "div",
                        "style": null,
                        "text": "This is the title element"
                    },
                    {
                        "id": 1,
                        "type": "pre",
                        "style": null,
                        "text": "This is pre block element"
                    },
                    {
                        "id": 2,
                        "type": "div",
                        "style": null,
                        "text": "This is paragraph entery"
                    }
                ],
                "comments": null
            },
            {
                "id": 2,
                "titleText": "Snippet 3",
                "elements": [
                    {
                        "id": 0,
                        "type": "div",
                        "style": null,
                        "text": "This is the title element"
                    },
                    {
                        "id": 1,
                        "type": "pre",
                        "style": null,
                        "text": "This is pre block element"
                    },
                    {
                        "id": 2,
                        "type": "div",
                        "style": null,
                        "text": "This is paragraph entery"
                    }
                ],
                "comments": null
            }
        ]
    }
]